better_tables
