Metadata-Version: 1.1
Name: BetterTablesExtension
Version: 0.0.2
Summary: Python-Markdown extension to add additional table options
Home-page: http://neurobashing.com/
Author: Gregg Thomason
Author-email: gregg@neurobashing.com
License: UNKNOWN
Platform: UNKNOWN
Classifier: Development Status :: 4 - Beta
Classifier: Operating System :: OS Independent
Classifier: License :: OSI Approved :: BSD License
Classifier: Intended Audience :: Developers
Classifier: Environment :: Web Environment
Classifier: Programming Language :: Python
Classifier: Topic :: Text Processing :: Filters
Classifier: Topic :: Text Processing :: Markup :: HTML
